README.txt
distribute_setup.py
setup.py
RSCloud.egg-info/PKG-INFO
RSCloud.egg-info/SOURCES.txt
RSCloud.egg-info/dependency_links.txt
RSCloud.egg-info/requires.txt
RSCloud.egg-info/top_level.txt
rscloud/Auth1.py
rscloud/Auth2.py
rscloud/Cloud.py
rscloud/CloudBS.py
rscloud/CloudDB.py
rscloud/CloudDNS.py
rscloud/CloudFiles.py
rscloud/CloudLB.py
rscloud/CloudMonitor.py
rscloud/CloudNetworks.py
rscloud/CloudServersFG.py
rscloud/CloudServersNG.py
rscloud/ListOps.py
rscloud/__init__.py
rscloud/bin/_Exceptions.py
rscloud/bin/_Globals.py
rscloud/bin/__init__.py