Metadata-Version: 1.1
Name: RSCloud
Version: 1.0.12
Summary: Rackspace Cloud Python Bindings
Home-page: http://pypi.python.org/pypi/RSCloud
Author: Rackspace SMB Operations
Author-email: ['Nathan.House@RACKSPACE.com', 'Samuel.Stavinoha@RACKSPACE.com', 'Zak.Jones@RACKSPACE.com']
License: Apache License 2.0
Keywords: rackspace,cloud,python bindings
Platform: UNKNOWN
Classifier: Development Status :: 4 - Beta
Classifier: Intended Audience :: Developers
Classifier: Intended Audience :: System Administrators
Classifier: Intended Audience :: Information Technology
Classifier: License :: OSI Approved :: Apache Software License
Classifier: Operating System :: OS Independent
Classifier: Programming Language :: Python
Classifier: Topic :: Software Development
Classifier: Topic :: Database
Classifier: Topic :: Internet
Classifier: Topic :: Software Development :: Libraries :: Python Modules
Classifier: Topic :: Software Development :: Libraries :: Application Frameworks
